[
  {
    "word": "The",
    "start": 0,
    "end": 0.151
  },
  {
    "word": "Shared",
    "start": 0.197,
    "end": 0.476
  },
  {
    "word": "Branches",
    "start": 0.511,
    "end": 0.894
  },
  {
    "word": "tab",
    "start": 0.94,
    "end": 1.196
  },
  {
    "word": "controls",
    "start": 1.254,
    "end": 1.695
  },
  {
    "word": "which",
    "start": 1.73,
    "end": 1.916
  },
  {
    "word": "branches",
    "start": 1.997,
    "end": 2.426
  },
  {
    "word": "beyond",
    "start": 2.496,
    "end": 2.891
  },
  {
    "word": "the",
    "start": 2.937,
    "end": 3.007
  },
  {
    "word": "employee's",
    "start": 3.053,
    "end": 3.541
  },
  {
    "word": "home",
    "start": 3.587,
    "end": 3.82
  },
  {
    "word": "branch",
    "start": 3.843,
    "end": 4.145
  },
  {
    "word": "can",
    "start": 4.191,
    "end": 4.331
  },
  {
    "word": "see",
    "start": 4.412,
    "end": 4.737
  },
  {
    "word": "and",
    "start": 4.795,
    "end": 4.946
  },
  {
    "word": "schedule",
    "start": 5.016,
    "end": 5.457
  },
  {
    "word": "them.",
    "start": 5.492,
    "end": 5.805
  },
  {
    "word": "When",
    "start": 5.805,
    "end": 6.002
  },
  {
    "word": "an",
    "start": 6.049,
    "end": 6.095
  },
  {
    "word": "employee",
    "start": 6.13,
    "end": 6.618
  },
  {
    "word": "is",
    "start": 6.687,
    "end": 6.792
  },
  {
    "word": "shared",
    "start": 6.85,
    "end": 7.163
  },
  {
    "word": "to",
    "start": 7.187,
    "end": 7.268
  },
  {
    "word": "another",
    "start": 7.349,
    "end": 7.605
  },
  {
    "word": "branch:",
    "start": 7.639,
    "end": 8.986
  },
  {
    "word": "•",
    "start": 8.986,
    "end": 11.784
  },
  {
    "word": "That",
    "start": 12.736,
    "end": 13.003
  },
  {
    "word": "branch",
    "start": 13.073,
    "end": 13.421
  },
  {
    "word": "can",
    "start": 13.468,
    "end": 13.607
  },
  {
    "word": "search",
    "start": 13.688,
    "end": 13.955
  },
  {
    "word": "for",
    "start": 14.002,
    "end": 14.106
  },
  {
    "word": "them",
    "start": 14.164,
    "end": 14.35
  },
  {
    "word": "in",
    "start": 14.443,
    "end": 14.571
  },
  {
    "word": "Manage",
    "start": 14.663,
    "end": 14.988
  },
  {
    "word": "Employee",
    "start": 15.012,
    "end": 15.65
  },
  {
    "word": "•",
    "start": 15.65,
    "end": 15.975
  },
  {
    "word": "That",
    "start": 16.358,
    "end": 16.602
  },
  {
    "word": "branch",
    "start": 16.672,
    "end": 17.009
  },
  {
    "word": "can",
    "start": 17.055,
    "end": 17.183
  },
  {
    "word": "schedule",
    "start": 17.241,
    "end": 17.613
  },
  {
    "word": "them",
    "start": 17.636,
    "end": 17.763
  },
  {
    "word": "for",
    "start": 17.822,
    "end": 17.926
  },
  {
    "word": "their",
    "start": 17.961,
    "end": 18.112
  },
  {
    "word": "jobs",
    "start": 18.158,
    "end": 18.75
  },
  {
    "word": "•",
    "start": 18.75,
    "end": 18.808
  },
  {
    "word": "The",
    "start": 19.087,
    "end": 19.215
  },
  {
    "word": "employee's",
    "start": 19.261,
    "end": 20.004
  },
  {
    "word": "record",
    "start": 20.364,
    "end": 20.805
  },
  {
    "word": "and",
    "start": 21.061,
    "end": 21.397
  },
  {
    "word": "pay",
    "start": 21.502,
    "end": 21.792
  },
  {
    "word": "rate",
    "start": 21.955,
    "end": 22.21
  },
  {
    "word": "information",
    "start": 22.257,
    "end": 22.872
  },
  {
    "word": "becomes",
    "start": 23.429,
    "end": 23.94
  },
  {
    "word": "visible",
    "start": 24.044,
    "end": 24.509
  },
  {
    "word": "to",
    "start": 24.544,
    "end": 24.637
  },
  {
    "word": "that",
    "start": 24.695,
    "end": 24.834
  },
  {
    "word": "branch",
    "start": 24.892,
    "end": 25.832
  },
  {
    "word": "Common",
    "start": 25.832,
    "end": 26.216
  },
  {
    "word": "use",
    "start": 26.274,
    "end": 26.436
  },
  {
    "word": "cases:",
    "start": 26.471,
    "end": 27.481
  },
  {
    "word": "•",
    "start": 27.481,
    "end": 27.597
  },
  {
    "word": "Large",
    "start": 27.853,
    "end": 28.247
  },
  {
    "word": "events",
    "start": 28.294,
    "end": 28.747
  },
  {
    "word": "where",
    "start": 29.141,
    "end": 29.397
  },
  {
    "word": "staff",
    "start": 29.455,
    "end": 29.931
  },
  {
    "word": "from",
    "start": 30.082,
    "end": 30.267
  },
  {
    "word": "multiple",
    "start": 30.337,
    "end": 30.743
  },
  {
    "word": "locations",
    "start": 30.778,
    "end": 31.417
  },
  {
    "word": "are",
    "start": 31.533,
    "end": 31.742
  },
  {
    "word": "needed",
    "start": 31.8,
    "end": 32.241
  },
  {
    "word": "•",
    "start": 32.241,
    "end": 32.717
  },
  {
    "word": "Employees",
    "start": 32.903,
    "end": 33.785
  },
  {
    "word": "who",
    "start": 34.134,
    "end": 34.377
  },
  {
    "word": "regularly",
    "start": 34.54,
    "end": 35.086
  },
  {
    "word": "work",
    "start": 35.144,
    "end": 35.411
  },
  {
    "word": "across",
    "start": 35.48,
    "end": 35.898
  },
  {
    "word": "multiple",
    "start": 36.014,
    "end": 36.478
  },
  {
    "word": "branches",
    "start": 36.525,
    "end": 37.605
  },
  {
    "word": "Add",
    "start": 37.605,
    "end": 37.848
  },
  {
    "word": "branches",
    "start": 37.895,
    "end": 38.301
  },
  {
    "word": "carefully",
    "start": 38.359,
    "end": 38.87
  },
  {
    "word": "—",
    "start": 38.986,
    "end": 39.033
  },
  {
    "word": "sharing",
    "start": 39.242,
    "end": 39.811
  },
  {
    "word": "an",
    "start": 40.054,
    "end": 40.252
  },
  {
    "word": "employee",
    "start": 40.298,
    "end": 41.053
  },
  {
    "word": "gives",
    "start": 41.227,
    "end": 41.587
  },
  {
    "word": "another",
    "start": 41.68,
    "end": 42.121
  },
  {
    "word": "branch",
    "start": 42.179,
    "end": 42.574
  },
  {
    "word": "access",
    "start": 42.69,
    "end": 43.224
  },
  {
    "word": "to",
    "start": 43.27,
    "end": 43.398
  },
  {
    "word": "their",
    "start": 43.491,
    "end": 43.665
  },
  {
    "word": "record",
    "start": 43.746,
    "end": 44.037
  },
  {
    "word": "information.",
    "start": 44.071,
    "end": 44.768
  },
  {
    "word": "Remove",
    "start": 45.093,
    "end": 45.627
  },
  {
    "word": "the",
    "start": 45.674,
    "end": 45.743
  },
  {
    "word": "sharing",
    "start": 45.79,
    "end": 46.254
  },
  {
    "word": "when",
    "start": 46.533,
    "end": 46.718
  },
  {
    "word": "it's",
    "start": 46.753,
    "end": 46.881
  },
  {
    "word": "no",
    "start": 46.927,
    "end": 47.009
  },
  {
    "word": "longer",
    "start": 47.09,
    "end": 47.345
  },
  {
    "word": "needed.",
    "start": 47.403,
    "end": 48.019
  }
]