[
  {
    "word": "Go",
    "start": 0,
    "end": 0.174
  },
  {
    "word": "to",
    "start": 0.232,
    "end": 0.279
  },
  {
    "word": "Reports",
    "start": 0.36,
    "end": 0.836
  },
  {
    "word": "→",
    "start": 0.964,
    "end": 1.022
  },
  {
    "word": "Payroll",
    "start": 1.265,
    "end": 1.614
  },
  {
    "word": "Reports",
    "start": 1.672,
    "end": 2.09
  },
  {
    "word": "to",
    "start": 2.136,
    "end": 2.206
  },
  {
    "word": "access",
    "start": 2.299,
    "end": 2.717
  },
  {
    "word": "this",
    "start": 2.752,
    "end": 2.868
  },
  {
    "word": "section.",
    "start": 2.902,
    "end": 3.437
  },
  {
    "word": "Reports",
    "start": 3.437,
    "end": 3.843
  },
  {
    "word": "available",
    "start": 3.878,
    "end": 4.331
  },
  {
    "word": "here:",
    "start": 4.377,
    "end": 4.899
  },
  {
    "word": "•",
    "start": 4.899,
    "end": 4.934
  },
  {
    "word": "Employee",
    "start": 5.004,
    "end": 5.538
  },
  {
    "word": "Time",
    "start": 5.596,
    "end": 5.851
  },
  {
    "word": "Register",
    "start": 5.886,
    "end": 6.281
  },
  {
    "word": "—",
    "start": 6.316,
    "end": 6.374
  },
  {
    "word": "the",
    "start": 6.432,
    "end": 6.502
  },
  {
    "word": "primary",
    "start": 6.56,
    "end": 6.966
  },
  {
    "word": "report.",
    "start": 7.047,
    "end": 7.523
  },
  {
    "word": "Shows",
    "start": 7.697,
    "end": 8.034
  },
  {
    "word": "each",
    "start": 8.115,
    "end": 8.313
  },
  {
    "word": "employee's",
    "start": 8.359,
    "end": 8.812
  },
  {
    "word": "hours",
    "start": 8.87,
    "end": 9.195
  },
  {
    "word": "worked",
    "start": 9.265,
    "end": 9.509
  },
  {
    "word": "by",
    "start": 9.543,
    "end": 9.671
  },
  {
    "word": "job",
    "start": 9.787,
    "end": 10.077
  },
  {
    "word": "and",
    "start": 10.136,
    "end": 10.217
  },
  {
    "word": "shift.",
    "start": 10.275,
    "end": 10.809
  },
  {
    "word": "•",
    "start": 10.809,
    "end": 10.925
  },
  {
    "word": "Employee",
    "start": 10.971,
    "end": 11.494
  },
  {
    "word": "Time",
    "start": 11.552,
    "end": 11.819
  },
  {
    "word": "Register",
    "start": 11.854,
    "end": 12.225
  },
  {
    "word": "(Break)",
    "start": 12.283,
    "end": 12.794
  },
  {
    "word": "—",
    "start": 12.968,
    "end": 13.038
  },
  {
    "word": "same",
    "start": 13.131,
    "end": 13.41
  },
  {
    "word": "as",
    "start": 13.433,
    "end": 13.514
  },
  {
    "word": "above,",
    "start": 13.584,
    "end": 14.094
  },
  {
    "word": "with",
    "start": 14.303,
    "end": 14.478
  },
  {
    "word": "break",
    "start": 14.536,
    "end": 14.768
  },
  {
    "word": "time",
    "start": 14.814,
    "end": 15.07
  },
  {
    "word": "broken",
    "start": 15.105,
    "end": 15.406
  },
  {
    "word": "out",
    "start": 15.453,
    "end": 15.569
  },
  {
    "word": "separately.",
    "start": 15.615,
    "end": 17.067
  },
  {
    "word": "•",
    "start": 17.067,
    "end": 19.4
  },
  {
    "word": "Emp",
    "start": 20.329,
    "end": 21.606
  },
  {
    "word": "Time",
    "start": 22.547,
    "end": 23.057
  },
  {
    "word": "Register",
    "start": 23.232,
    "end": 23.777
  },
  {
    "word": "With",
    "start": 24.706,
    "end": 24.892
  },
  {
    "word": "Notes",
    "start": 24.961,
    "end": 25.287
  },
  {
    "word": "—",
    "start": 25.368,
    "end": 25.403
  },
  {
    "word": "includes",
    "start": 25.437,
    "end": 25.832
  },
  {
    "word": "any",
    "start": 25.89,
    "end": 26.064
  },
  {
    "word": "notes",
    "start": 26.134,
    "end": 26.343
  },
  {
    "word": "attached",
    "start": 26.366,
    "end": 26.715
  },
  {
    "word": "to",
    "start": 26.726,
    "end": 26.773
  },
  {
    "word": "an",
    "start": 26.831,
    "end": 26.889
  },
  {
    "word": "employee's",
    "start": 26.912,
    "end": 27.4
  },
  {
    "word": "timesheet",
    "start": 27.446,
    "end": 27.887
  },
  {
    "word": "entry.",
    "start": 27.945,
    "end": 28.711
  },
  {
    "word": "•",
    "start": 28.711,
    "end": 28.723
  },
  {
    "word": "Financial",
    "start": 28.828,
    "end": 29.304
  },
  {
    "word": "Analysis",
    "start": 29.35,
    "end": 29.768
  },
  {
    "word": "Report",
    "start": 29.826,
    "end": 30.163
  },
  {
    "word": "—",
    "start": 30.221,
    "end": 30.256
  },
  {
    "word": "a",
    "start": 30.302,
    "end": 30.383
  },
  {
    "word": "cost-facing",
    "start": 30.476,
    "end": 31.15
  },
  {
    "word": "view",
    "start": 31.196,
    "end": 31.359
  },
  {
    "word": "of",
    "start": 31.393,
    "end": 31.44
  },
  {
    "word": "hours",
    "start": 31.498,
    "end": 31.811
  },
  {
    "word": "and",
    "start": 31.846,
    "end": 31.927
  },
  {
    "word": "pay",
    "start": 31.974,
    "end": 32.136
  },
  {
    "word": "across",
    "start": 32.183,
    "end": 32.473
  },
  {
    "word": "jobs.",
    "start": 32.52,
    "end": 33.286
  },
  {
    "word": "•",
    "start": 33.286,
    "end": 33.321
  },
  {
    "word": "Export",
    "start": 33.472,
    "end": 33.959
  },
  {
    "word": "PerDiem",
    "start": 34.006,
    "end": 34.412
  },
  {
    "word": "Report",
    "start": 34.482,
    "end": 34.853
  },
  {
    "word": "—",
    "start": 34.9,
    "end": 34.993
  },
  {
    "word": "exports",
    "start": 35.109,
    "end": 35.596
  },
  {
    "word": "per",
    "start": 35.643,
    "end": 35.747
  },
  {
    "word": "diem",
    "start": 35.794,
    "end": 36.003
  },
  {
    "word": "payments",
    "start": 36.049,
    "end": 36.397
  },
  {
    "word": "for",
    "start": 36.432,
    "end": 36.525
  },
  {
    "word": "payroll",
    "start": 36.56,
    "end": 36.827
  },
  {
    "word": "processing.",
    "start": 36.862,
    "end": 37.744
  },
  {
    "word": "•",
    "start": 37.744,
    "end": 37.767
  },
  {
    "word": "Manage",
    "start": 37.884,
    "end": 38.29
  },
  {
    "word": "Temp",
    "start": 38.325,
    "end": 38.534
  },
  {
    "word": "Cost",
    "start": 38.592,
    "end": 38.894
  },
  {
    "word": "Code",
    "start": 38.94,
    "end": 39.195
  },
  {
    "word": "Number",
    "start": 39.242,
    "end": 39.521
  },
  {
    "word": "—",
    "start": 39.567,
    "end": 39.613
  },
  {
    "word": "for",
    "start": 39.671,
    "end": 39.799
  },
  {
    "word": "branches",
    "start": 39.846,
    "end": 40.252
  },
  {
    "word": "that",
    "start": 40.287,
    "end": 40.403
  },
  {
    "word": "use",
    "start": 40.473,
    "end": 40.67
  },
  {
    "word": "cost",
    "start": 40.728,
    "end": 41.03
  },
  {
    "word": "codes",
    "start": 41.076,
    "end": 41.39
  },
  {
    "word": "to",
    "start": 41.436,
    "end": 41.494
  },
  {
    "word": "categorize",
    "start": 41.564,
    "end": 42.156
  },
  {
    "word": "labor.",
    "start": 42.202,
    "end": 42.806
  },
  {
    "word": "•",
    "start": 42.806,
    "end": 42.887
  },
  {
    "word": "Employee",
    "start": 42.98,
    "end": 43.584
  },
  {
    "word": "Estimate",
    "start": 43.665,
    "end": 44.06
  },
  {
    "word": "Hours",
    "start": 44.083,
    "end": 44.466
  },
  {
    "word": "—",
    "start": 44.583,
    "end": 44.641
  },
  {
    "word": "projected",
    "start": 44.791,
    "end": 45.418
  },
  {
    "word": "hours",
    "start": 45.453,
    "end": 45.767
  },
  {
    "word": "based",
    "start": 45.825,
    "end": 46.069
  },
  {
    "word": "on",
    "start": 46.115,
    "end": 46.196
  },
  {
    "word": "scheduled",
    "start": 46.254,
    "end": 46.695
  },
  {
    "word": "shifts",
    "start": 46.73,
    "end": 47.102
  },
  {
    "word": "before",
    "start": 47.16,
    "end": 47.461
  },
  {
    "word": "actuals",
    "start": 47.508,
    "end": 47.961
  },
  {
    "word": "are",
    "start": 47.996,
    "end": 48.1
  },
  {
    "word": "entered.",
    "start": 48.135,
    "end": 48.704
  },
  {
    "word": "For",
    "start": 48.704,
    "end": 48.855
  },
  {
    "word": "most",
    "start": 48.913,
    "end": 49.087
  },
  {
    "word": "day-to-day",
    "start": 49.157,
    "end": 49.516
  },
  {
    "word": "payroll",
    "start": 49.586,
    "end": 50.109
  },
  {
    "word": "review,",
    "start": 50.259,
    "end": 51.037
  },
  {
    "word": "you'll",
    "start": 51.165,
    "end": 51.374
  },
  {
    "word": "be",
    "start": 51.42,
    "end": 51.49
  },
  {
    "word": "working",
    "start": 51.525,
    "end": 51.815
  },
  {
    "word": "with",
    "start": 51.862,
    "end": 52.013
  },
  {
    "word": "the",
    "start": 52.059,
    "end": 52.164
  },
  {
    "word": "Employee",
    "start": 52.256,
    "end": 52.628
  },
  {
    "word": "Time",
    "start": 52.686,
    "end": 52.953
  },
  {
    "word": "Register.",
    "start": 52.988,
    "end": 53.731
  }
]