[
  {
    "word": "The",
    "start": 0,
    "end": 0.151
  },
  {
    "word": "Disciplinary",
    "start": 0.197,
    "end": 0.731
  },
  {
    "word": "Action",
    "start": 0.801,
    "end": 1.091
  },
  {
    "word": "tab",
    "start": 1.149,
    "end": 1.474
  },
  {
    "word": "is",
    "start": 1.556,
    "end": 1.66
  },
  {
    "word": "where",
    "start": 1.707,
    "end": 1.892
  },
  {
    "word": "formal",
    "start": 1.974,
    "end": 2.368
  },
  {
    "word": "disciplinary",
    "start": 2.438,
    "end": 3.053
  },
  {
    "word": "records",
    "start": 3.17,
    "end": 3.622
  },
  {
    "word": "are",
    "start": 3.692,
    "end": 3.889
  },
  {
    "word": "logged",
    "start": 3.959,
    "end": 4.365
  },
  {
    "word": "for",
    "start": 4.447,
    "end": 4.725
  },
  {
    "word": "an",
    "start": 4.853,
    "end": 4.992
  },
  {
    "word": "employee.",
    "start": 5.039,
    "end": 5.817
  },
  {
    "word": "What",
    "start": 5.817,
    "end": 5.991
  },
  {
    "word": "you",
    "start": 6.049,
    "end": 6.118
  },
  {
    "word": "can",
    "start": 6.165,
    "end": 6.281
  },
  {
    "word": "do",
    "start": 6.339,
    "end": 6.478
  },
  {
    "word": "here:",
    "start": 6.56,
    "end": 7.024
  },
  {
    "word": "•",
    "start": 7.024,
    "end": 7.07
  },
  {
    "word": "View",
    "start": 7.279,
    "end": 7.593
  },
  {
    "word": "the",
    "start": 7.674,
    "end": 7.744
  },
  {
    "word": "full",
    "start": 7.802,
    "end": 8.011
  },
  {
    "word": "history",
    "start": 8.081,
    "end": 8.51
  },
  {
    "word": "of",
    "start": 8.603,
    "end": 8.754
  },
  {
    "word": "disciplinary",
    "start": 8.87,
    "end": 9.497
  },
  {
    "word": "actions",
    "start": 9.567,
    "end": 10.031
  },
  {
    "word": "on",
    "start": 10.147,
    "end": 10.344
  },
  {
    "word": "file",
    "start": 10.426,
    "end": 10.925
  },
  {
    "word": "•",
    "start": 10.925,
    "end": 11.738
  },
  {
    "word": "Add",
    "start": 12.179,
    "end": 12.376
  },
  {
    "word": "a",
    "start": 12.423,
    "end": 12.446
  },
  {
    "word": "new",
    "start": 12.527,
    "end": 12.678
  },
  {
    "word": "disciplinary",
    "start": 12.736,
    "end": 13.27
  },
  {
    "word": "action",
    "start": 13.34,
    "end": 13.618
  },
  {
    "word": "record",
    "start": 13.688,
    "end": 14.373
  },
  {
    "word": "When",
    "start": 14.373,
    "end": 14.571
  },
  {
    "word": "adding",
    "start": 14.617,
    "end": 14.826
  },
  {
    "word": "a",
    "start": 14.872,
    "end": 14.896
  },
  {
    "word": "new",
    "start": 14.954,
    "end": 15.07
  },
  {
    "word": "record,",
    "start": 15.151,
    "end": 15.581
  },
  {
    "word": "fill",
    "start": 15.697,
    "end": 15.941
  },
  {
    "word": "in:",
    "start": 16.022,
    "end": 16.509
  },
  {
    "word": "•",
    "start": 16.509,
    "end": 16.533
  },
  {
    "word": "Date",
    "start": 16.858,
    "end": 17.229
  },
  {
    "word": "—",
    "start": 17.357,
    "end": 17.403
  },
  {
    "word": "the",
    "start": 17.833,
    "end": 17.949
  },
  {
    "word": "date",
    "start": 18.03,
    "end": 18.297
  },
  {
    "word": "the",
    "start": 18.332,
    "end": 18.414
  },
  {
    "word": "action",
    "start": 18.483,
    "end": 18.785
  },
  {
    "word": "occurred",
    "start": 18.82,
    "end": 19.366
  },
  {
    "word": "•",
    "start": 19.366,
    "end": 19.609
  },
  {
    "word": "Type",
    "start": 19.992,
    "end": 20.48
  },
  {
    "word": "—",
    "start": 20.538,
    "end": 20.608
  },
  {
    "word": "the",
    "start": 21.049,
    "end": 21.142
  },
  {
    "word": "category",
    "start": 21.188,
    "end": 21.688
  },
  {
    "word": "of",
    "start": 21.734,
    "end": 21.78
  },
  {
    "word": "disciplinary",
    "start": 21.838,
    "end": 22.419
  },
  {
    "word": "action",
    "start": 22.489,
    "end": 23.057
  },
  {
    "word": "•",
    "start": 23.057,
    "end": 23.116
  },
  {
    "word": "Notes",
    "start": 23.557,
    "end": 23.998
  },
  {
    "word": "—",
    "start": 24.242,
    "end": 24.381
  },
  {
    "word": "a",
    "start": 24.764,
    "end": 24.822
  },
  {
    "word": "clear",
    "start": 24.915,
    "end": 25.136
  },
  {
    "word": "description",
    "start": 25.182,
    "end": 25.658
  },
  {
    "word": "of",
    "start": 25.705,
    "end": 25.751
  },
  {
    "word": "what",
    "start": 25.797,
    "end": 25.937
  },
  {
    "word": "happened",
    "start": 25.995,
    "end": 26.39
  },
  {
    "word": "and",
    "start": 26.459,
    "end": 26.575
  },
  {
    "word": "any",
    "start": 26.645,
    "end": 26.842
  },
  {
    "word": "actions",
    "start": 26.912,
    "end": 27.307
  },
  {
    "word": "taken",
    "start": 27.365,
    "end": 28.468
  },
  {
    "word": "Be",
    "start": 28.468,
    "end": 28.665
  },
  {
    "word": "precise",
    "start": 28.746,
    "end": 29.397
  },
  {
    "word": "and",
    "start": 29.455,
    "end": 29.617
  },
  {
    "word": "factual",
    "start": 29.733,
    "end": 30.395
  },
  {
    "word": "when",
    "start": 30.488,
    "end": 30.662
  },
  {
    "word": "writing",
    "start": 30.72,
    "end": 31.057
  },
  {
    "word": "notes.",
    "start": 31.126,
    "end": 31.591
  },
  {
    "word": "These",
    "start": 31.974,
    "end": 32.253
  },
  {
    "word": "records",
    "start": 32.322,
    "end": 32.717
  },
  {
    "word": "are",
    "start": 32.763,
    "end": 32.891
  },
  {
    "word": "part",
    "start": 32.937,
    "end": 33.112
  },
  {
    "word": "of",
    "start": 33.146,
    "end": 33.193
  },
  {
    "word": "the",
    "start": 33.228,
    "end": 33.297
  },
  {
    "word": "employee's",
    "start": 33.355,
    "end": 33.913
  },
  {
    "word": "permanent",
    "start": 33.982,
    "end": 34.354
  },
  {
    "word": "file",
    "start": 34.412,
    "end": 34.923
  },
  {
    "word": "and",
    "start": 35.074,
    "end": 35.457
  },
  {
    "word": "may",
    "start": 35.573,
    "end": 35.759
  },
  {
    "word": "be",
    "start": 35.84,
    "end": 36.072
  },
  {
    "word": "referenced",
    "start": 36.2,
    "end": 36.687
  },
  {
    "word": "during",
    "start": 36.711,
    "end": 36.954
  },
  {
    "word": "reviews",
    "start": 37.129,
    "end": 37.779
  },
  {
    "word": "or",
    "start": 37.953,
    "end": 38.243
  },
  {
    "word": "investigations.",
    "start": 38.394,
    "end": 39.787
  },
  {
    "word": "Click",
    "start": 39.787,
    "end": 40.054
  },
  {
    "word": "Save",
    "start": 40.124,
    "end": 40.461
  },
  {
    "word": "after",
    "start": 40.507,
    "end": 40.902
  },
  {
    "word": "entering",
    "start": 41.018,
    "end": 41.471
  },
  {
    "word": "the",
    "start": 41.587,
    "end": 41.726
  },
  {
    "word": "record.",
    "start": 41.807,
    "end": 42.446
  }
]