[
  {
    "word": "Open",
    "start": 0,
    "end": 0.325
  },
  {
    "word": "a",
    "start": 0.383,
    "end": 0.418
  },
  {
    "word": "shift",
    "start": 0.464,
    "end": 0.708
  },
  {
    "word": "role.",
    "start": 0.755,
    "end": 1.033
  },
  {
    "word": "If",
    "start": 1.057,
    "end": 1.196
  },
  {
    "word": "electronic",
    "start": 1.265,
    "end": 1.823
  },
  {
    "word": "sign-ins",
    "start": 1.881,
    "end": 2.276
  },
  {
    "word": "were",
    "start": 2.322,
    "end": 2.508
  },
  {
    "word": "completed,",
    "start": 2.554,
    "end": 3.088
  },
  {
    "word": "those",
    "start": 3.146,
    "end": 3.39
  },
  {
    "word": "times",
    "start": 3.425,
    "end": 3.727
  },
  {
    "word": "are",
    "start": 3.762,
    "end": 3.913
  },
  {
    "word": "already",
    "start": 3.982,
    "end": 4.389
  },
  {
    "word": "populated",
    "start": 4.47,
    "end": 5.016
  },
  {
    "word": "for",
    "start": 5.062,
    "end": 5.19
  },
  {
    "word": "each",
    "start": 5.306,
    "end": 5.515
  },
  {
    "word": "employee.",
    "start": 5.561,
    "end": 6.281
  },
  {
    "word": "Review",
    "start": 6.281,
    "end": 6.583
  },
  {
    "word": "the",
    "start": 6.641,
    "end": 6.711
  },
  {
    "word": "times.",
    "start": 6.757,
    "end": 7.163
  },
  {
    "word": "If",
    "start": 7.187,
    "end": 7.326
  },
  {
    "word": "everything",
    "start": 7.396,
    "end": 7.814
  },
  {
    "word": "looks",
    "start": 7.883,
    "end": 8.092
  },
  {
    "word": "correct,",
    "start": 8.15,
    "end": 8.615
  },
  {
    "word": "click",
    "start": 8.673,
    "end": 9.021
  },
  {
    "word": "Approve",
    "start": 9.137,
    "end": 9.625
  },
  {
    "word": "Hours",
    "start": 9.659,
    "end": 10.054
  },
  {
    "word": "—",
    "start": 10.101,
    "end": 10.147
  },
  {
    "word": "this",
    "start": 10.17,
    "end": 10.391
  },
  {
    "word": "is",
    "start": 10.449,
    "end": 10.542
  },
  {
    "word": "your",
    "start": 10.588,
    "end": 10.716
  },
  {
    "word": "save",
    "start": 10.774,
    "end": 11.029
  },
  {
    "word": "button",
    "start": 11.076,
    "end": 11.378
  },
  {
    "word": "and",
    "start": 11.459,
    "end": 11.61
  },
  {
    "word": "finalizes",
    "start": 11.726,
    "end": 12.469
  },
  {
    "word": "the",
    "start": 12.527,
    "end": 12.609
  },
  {
    "word": "hours.",
    "start": 12.667,
    "end": 13.131
  },
  {
    "word": "After",
    "start": 13.131,
    "end": 13.456
  },
  {
    "word": "approving,",
    "start": 13.514,
    "end": 13.967
  },
  {
    "word": "you",
    "start": 13.99,
    "end": 14.06
  },
  {
    "word": "will",
    "start": 14.095,
    "end": 14.223
  },
  {
    "word": "see",
    "start": 14.269,
    "end": 14.408
  },
  {
    "word": "green",
    "start": 14.49,
    "end": 14.792
  },
  {
    "word": "sunburst",
    "start": 14.873,
    "end": 15.349
  },
  {
    "word": "icons",
    "start": 15.395,
    "end": 16.022
  },
  {
    "word": "next",
    "start": 16.347,
    "end": 16.603
  },
  {
    "word": "to",
    "start": 16.649,
    "end": 16.823
  },
  {
    "word": "completed",
    "start": 16.939,
    "end": 17.648
  },
  {
    "word": "shifts.",
    "start": 17.764,
    "end": 18.379
  },
  {
    "word": "These",
    "start": 18.623,
    "end": 18.878
  },
  {
    "word": "let",
    "start": 18.925,
    "end": 19.041
  },
  {
    "word": "you",
    "start": 19.087,
    "end": 19.168
  },
  {
    "word": "track",
    "start": 19.215,
    "end": 19.435
  },
  {
    "word": "where",
    "start": 19.47,
    "end": 19.598
  },
  {
    "word": "you",
    "start": 19.633,
    "end": 19.703
  },
  {
    "word": "are:",
    "start": 19.784,
    "end": 20.097
  },
  {
    "word": "green",
    "start": 20.179,
    "end": 20.434
  },
  {
    "word": "means",
    "start": 20.492,
    "end": 20.771
  },
  {
    "word": "done,",
    "start": 20.864,
    "end": 21.34
  },
  {
    "word": "blue",
    "start": 21.456,
    "end": 21.734
  },
  {
    "word": "link",
    "start": 21.769,
    "end": 21.99
  },
  {
    "word": "means",
    "start": 22.071,
    "end": 22.442
  },
  {
    "word": "not",
    "start": 22.617,
    "end": 22.849
  },
  {
    "word": "yet",
    "start": 22.907,
    "end": 23.093
  },
  {
    "word": "processed.",
    "start": 23.162,
    "end": 24.103
  },
  {
    "word": "For",
    "start": 24.103,
    "end": 24.312
  },
  {
    "word": "paper",
    "start": 24.405,
    "end": 24.672
  },
  {
    "word": "sign-in",
    "start": 24.73,
    "end": 25.043
  },
  {
    "word": "sheets,",
    "start": 25.101,
    "end": 25.566
  },
  {
    "word": "use",
    "start": 25.809,
    "end": 26.03
  },
  {
    "word": "the",
    "start": 26.065,
    "end": 26.134
  },
  {
    "word": "Sign-In",
    "start": 26.204,
    "end": 26.587
  },
  {
    "word": "and",
    "start": 26.669,
    "end": 26.761
  },
  {
    "word": "Sign-Out",
    "start": 26.819,
    "end": 27.203
  },
  {
    "word": "buttons",
    "start": 27.261,
    "end": 27.621
  },
  {
    "word": "to",
    "start": 27.679,
    "end": 27.772
  },
  {
    "word": "populate",
    "start": 27.888,
    "end": 28.399
  },
  {
    "word": "all",
    "start": 28.445,
    "end": 28.666
  },
  {
    "word": "employees",
    "start": 28.724,
    "end": 29.269
  },
  {
    "word": "with",
    "start": 29.316,
    "end": 29.444
  },
  {
    "word": "the",
    "start": 29.467,
    "end": 29.536
  },
  {
    "word": "scheduled",
    "start": 29.56,
    "end": 29.943
  },
  {
    "word": "time,",
    "start": 29.966,
    "end": 30.512
  },
  {
    "word": "then",
    "start": 30.953,
    "end": 31.231
  },
  {
    "word": "use",
    "start": 31.44,
    "end": 31.719
  },
  {
    "word": "the",
    "start": 31.754,
    "end": 31.824
  },
  {
    "word": "tab",
    "start": 31.882,
    "end": 32.184
  },
  {
    "word": "key",
    "start": 32.253,
    "end": 32.462
  },
  {
    "word": "to",
    "start": 32.532,
    "end": 32.613
  },
  {
    "word": "manually",
    "start": 32.729,
    "end": 33.333
  },
  {
    "word": "adjust",
    "start": 33.403,
    "end": 33.96
  },
  {
    "word": "individual",
    "start": 34.053,
    "end": 34.668
  },
  {
    "word": "times.",
    "start": 34.726,
    "end": 35.481
  }
]