[
  {
    "word": "A",
    "start": 0,
    "end": 0.058
  },
  {
    "word": "few",
    "start": 0.139,
    "end": 0.267
  },
  {
    "word": "things",
    "start": 0.313,
    "end": 0.488
  },
  {
    "word": "to",
    "start": 0.511,
    "end": 0.557
  },
  {
    "word": "know:",
    "start": 0.604,
    "end": 1.173
  },
  {
    "word": "ГѓЖ’Г‚ВўГѓВўГўв‚¬ЕЎГ‚В¬ГѓвЂљГ‚Вў",
    "start": 1.173,
    "end": 5.248
  },
  {
    "word": "Red",
    "start": 5.492,
    "end": 5.619
  },
  {
    "word": "calendar",
    "start": 5.677,
    "end": 5.979
  },
  {
    "word": "highlights",
    "start": 6.037,
    "end": 6.385
  },
  {
    "word": "may",
    "start": 6.42,
    "end": 6.513
  },
  {
    "word": "indicate",
    "start": 6.56,
    "end": 6.861
  },
  {
    "word": "overtime,",
    "start": 6.896,
    "end": 7.407
  },
  {
    "word": "informational",
    "start": 7.465,
    "end": 7.953
  },
  {
    "word": "only,",
    "start": 8.011,
    "end": 8.359
  },
  {
    "word": "it",
    "start": 8.487,
    "end": 8.58
  },
  {
    "word": "will",
    "start": 8.615,
    "end": 8.742
  },
  {
    "word": "not",
    "start": 8.789,
    "end": 8.928
  },
  {
    "word": "prevent",
    "start": 8.963,
    "end": 9.207
  },
  {
    "word": "saving.",
    "start": 9.265,
    "end": 9.764
  },
  {
    "word": "ГѓЖ’Г‚ВўГѓВўГўв‚¬ЕЎГ‚В¬ГѓвЂљГ‚Вў",
    "start": 9.764,
    "end": 13.758
  },
  {
    "word": "You",
    "start": 14.002,
    "end": 14.095
  },
  {
    "word": "can",
    "start": 14.129,
    "end": 14.222
  },
  {
    "word": "set",
    "start": 14.269,
    "end": 14.443
  },
  {
    "word": "unavailability",
    "start": 14.524,
    "end": 15.139
  },
  {
    "word": "for",
    "start": 15.197,
    "end": 15.325
  },
  {
    "word": "an",
    "start": 15.36,
    "end": 15.406
  },
  {
    "word": "employee",
    "start": 15.441,
    "end": 15.766
  },
  {
    "word": "on",
    "start": 15.824,
    "end": 15.917
  },
  {
    "word": "vacation,",
    "start": 15.964,
    "end": 16.451
  },
  {
    "word": "the",
    "start": 16.486,
    "end": 16.567
  },
  {
    "word": "calendar",
    "start": 16.602,
    "end": 16.892
  },
  {
    "word": "shows",
    "start": 16.95,
    "end": 17.182
  },
  {
    "word": "red",
    "start": 17.264,
    "end": 17.426
  },
  {
    "word": "across",
    "start": 17.473,
    "end": 17.751
  },
  {
    "word": "those",
    "start": 17.786,
    "end": 17.96
  },
  {
    "word": "days.",
    "start": 17.995,
    "end": 18.564
  },
  {
    "word": "ГѓЖ’Г‚ВўГѓВўГўв‚¬ЕЎГ‚В¬ГѓвЂљГ‚Вў",
    "start": 18.564,
    "end": 22.209
  },
  {
    "word": "You",
    "start": 22.453,
    "end": 22.569
  },
  {
    "word": "can",
    "start": 22.616,
    "end": 22.697
  },
  {
    "word": "send",
    "start": 22.732,
    "end": 22.86
  },
  {
    "word": "a",
    "start": 22.894,
    "end": 22.918
  },
  {
    "word": "copy",
    "start": 22.976,
    "end": 23.243
  },
  {
    "word": "of",
    "start": 23.278,
    "end": 23.324
  },
  {
    "word": "the",
    "start": 23.359,
    "end": 23.428
  },
  {
    "word": "schedule",
    "start": 23.452,
    "end": 23.8
  },
  {
    "word": "directly",
    "start": 23.835,
    "end": 24.346
  },
  {
    "word": "to",
    "start": 24.404,
    "end": 24.462
  },
  {
    "word": "the",
    "start": 24.52,
    "end": 24.589
  },
  {
    "word": "employee",
    "start": 24.648,
    "end": 25.124
  },
  {
    "word": "from",
    "start": 25.17,
    "end": 25.309
  },
  {
    "word": "this",
    "start": 25.356,
    "end": 25.483
  },
  {
    "word": "screen",
    "start": 25.53,
    "end": 25.878
  },
  {
    "word": "before",
    "start": 25.948,
    "end": 26.226
  },
  {
    "word": "ending",
    "start": 26.273,
    "end": 26.482
  },
  {
    "word": "a",
    "start": 26.528,
    "end": 26.552
  },
  {
    "word": "call.",
    "start": 26.61,
    "end": 27.306
  },
  {
    "word": "ГѓЖ’Г‚ВўГѓВўГўв‚¬ЕЎГ‚В¬ГѓвЂљГ‚Вў",
    "start": 27.306,
    "end": 30.847
  },
  {
    "word": "The",
    "start": 31.091,
    "end": 31.219
  },
  {
    "word": "scheduling",
    "start": 31.265,
    "end": 31.753
  },
  {
    "word": "comments",
    "start": 31.811,
    "end": 32.24
  },
  {
    "word": "button",
    "start": 32.298,
    "end": 32.624
  },
  {
    "word": "(asterisk",
    "start": 32.751,
    "end": 33.552
  },
  {
    "word": "icon)",
    "start": 33.61,
    "end": 34.121
  },
  {
    "word": "lets",
    "start": 34.365,
    "end": 34.551
  },
  {
    "word": "you",
    "start": 34.586,
    "end": 34.667
  },
  {
    "word": "add",
    "start": 34.737,
    "end": 34.899
  },
  {
    "word": "notes",
    "start": 34.969,
    "end": 35.225
  },
  {
    "word": "that",
    "start": 35.271,
    "end": 35.41
  },
  {
    "word": "appear",
    "start": 35.445,
    "end": 35.747
  },
  {
    "word": "on",
    "start": 35.817,
    "end": 35.91
  },
  {
    "word": "sign-in",
    "start": 35.991,
    "end": 36.409
  },
  {
    "word": "sheets,",
    "start": 36.467,
    "end": 36.966
  },
  {
    "word": "for",
    "start": 37.14,
    "end": 37.279
  },
  {
    "word": "example,",
    "start": 37.349,
    "end": 38.057
  },
  {
    "word": "flagging",
    "start": 38.382,
    "end": 38.951
  },
  {
    "word": "an",
    "start": 39.009,
    "end": 39.067
  },
  {
    "word": "employee",
    "start": 39.114,
    "end": 40.031
  },
  {
    "word": "who",
    "start": 40.182,
    "end": 40.345
  },
  {
    "word": "will",
    "start": 40.391,
    "end": 40.577
  },
  {
    "word": "be",
    "start": 40.635,
    "end": 40.739
  },
  {
    "word": "late.",
    "start": 40.809,
    "end": 41.471
  }
]