[
  {
    "word": "Not",
    "start": 0,
    "end": 0.279
  },
  {
    "word": "sure",
    "start": 0.325,
    "end": 0.546
  },
  {
    "word": "which",
    "start": 0.592,
    "end": 0.778
  },
  {
    "word": "Mail",
    "start": 0.848,
    "end": 1.033
  },
  {
    "word": "By",
    "start": 1.091,
    "end": 1.219
  },
  {
    "word": "option",
    "start": 1.3,
    "end": 1.637
  },
  {
    "word": "to",
    "start": 1.695,
    "end": 1.776
  },
  {
    "word": "use?",
    "start": 1.892,
    "end": 2.485
  },
  {
    "word": "Here's",
    "start": 2.601,
    "end": 2.879
  },
  {
    "word": "a",
    "start": 2.914,
    "end": 2.949
  },
  {
    "word": "quick",
    "start": 3.042,
    "end": 3.274
  },
  {
    "word": "guide:",
    "start": 3.344,
    "end": 4.017
  },
  {
    "word": "\"I",
    "start": 4.017,
    "end": 4.203
  },
  {
    "word": "need",
    "start": 4.284,
    "end": 4.435
  },
  {
    "word": "to",
    "start": 4.47,
    "end": 4.528
  },
  {
    "word": "reach",
    "start": 4.609,
    "end": 4.795
  },
  {
    "word": "a",
    "start": 4.83,
    "end": 4.865
  },
  {
    "word": "specific",
    "start": 4.899,
    "end": 5.422
  },
  {
    "word": "employee",
    "start": 5.468,
    "end": 6.072
  },
  {
    "word": "or",
    "start": 6.13,
    "end": 6.293
  },
  {
    "word": "a",
    "start": 6.327,
    "end": 6.351
  },
  {
    "word": "few",
    "start": 6.397,
    "end": 6.536
  },
  {
    "word": "people",
    "start": 6.583,
    "end": 6.838
  },
  {
    "word": "by",
    "start": 6.873,
    "end": 7.012
  },
  {
    "word": "name.\"",
    "start": 7.094,
    "end": 8.429
  },
  {
    "word": "→",
    "start": 8.429,
    "end": 11.227
  },
  {
    "word": "Mail",
    "start": 11.343,
    "end": 11.552
  },
  {
    "word": "By",
    "start": 11.622,
    "end": 11.761
  },
  {
    "word": "Employee",
    "start": 11.807,
    "end": 13.34
  },
  {
    "word": "\"I",
    "start": 13.34,
    "end": 13.735
  },
  {
    "word": "have",
    "start": 13.827,
    "end": 13.967
  },
  {
    "word": "open",
    "start": 14.025,
    "end": 14.292
  },
  {
    "word": "shifts",
    "start": 14.373,
    "end": 14.71
  },
  {
    "word": "and",
    "start": 14.756,
    "end": 14.849
  },
  {
    "word": "need",
    "start": 14.907,
    "end": 15.07
  },
  {
    "word": "to",
    "start": 15.105,
    "end": 15.151
  },
  {
    "word": "find",
    "start": 15.197,
    "end": 15.395
  },
  {
    "word": "employees",
    "start": 15.441,
    "end": 15.906
  },
  {
    "word": "who",
    "start": 15.94,
    "end": 16.057
  },
  {
    "word": "aren't",
    "start": 16.126,
    "end": 16.358
  },
  {
    "word": "scheduled",
    "start": 16.393,
    "end": 16.788
  },
  {
    "word": "yet.\"",
    "start": 16.834,
    "end": 18.158
  },
  {
    "word": "→",
    "start": 18.158,
    "end": 18.483
  },
  {
    "word": "Mail",
    "start": 18.634,
    "end": 18.889
  },
  {
    "word": "By",
    "start": 18.959,
    "end": 19.133
  },
  {
    "word": "Available",
    "start": 19.203,
    "end": 19.644
  },
  {
    "word": "Employee",
    "start": 19.679,
    "end": 20.573
  },
  {
    "word": "\"I",
    "start": 20.573,
    "end": 20.874
  },
  {
    "word": "need",
    "start": 20.967,
    "end": 21.142
  },
  {
    "word": "to",
    "start": 21.176,
    "end": 21.223
  },
  {
    "word": "send",
    "start": 21.281,
    "end": 21.443
  },
  {
    "word": "the",
    "start": 21.478,
    "end": 21.548
  },
  {
    "word": "same",
    "start": 21.583,
    "end": 21.803
  },
  {
    "word": "message",
    "start": 21.827,
    "end": 22.372
  },
  {
    "word": "to",
    "start": 22.523,
    "end": 22.651
  },
  {
    "word": "everyone",
    "start": 22.732,
    "end": 23.08
  },
  {
    "word": "working",
    "start": 23.127,
    "end": 23.58
  },
  {
    "word": "a",
    "start": 23.789,
    "end": 23.881
  },
  {
    "word": "specific",
    "start": 23.951,
    "end": 24.45
  },
  {
    "word": "job.\"",
    "start": 24.497,
    "end": 25.669
  },
  {
    "word": "→",
    "start": 25.669,
    "end": 25.704
  },
  {
    "word": "Mail",
    "start": 25.832,
    "end": 26.099
  },
  {
    "word": "By",
    "start": 26.18,
    "end": 26.354
  },
  {
    "word": "Job",
    "start": 26.436,
    "end": 27.55
  },
  {
    "word": "A",
    "start": 27.55,
    "end": 27.666
  },
  {
    "word": "few",
    "start": 27.782,
    "end": 27.968
  },
  {
    "word": "things",
    "start": 28.038,
    "end": 28.514
  },
  {
    "word": "to",
    "start": 28.688,
    "end": 28.792
  },
  {
    "word": "keep",
    "start": 28.862,
    "end": 29.036
  },
  {
    "word": "in",
    "start": 29.094,
    "end": 29.152
  },
  {
    "word": "mind:",
    "start": 29.21,
    "end": 30.116
  },
  {
    "word": "•",
    "start": 30.116,
    "end": 30.325
  },
  {
    "word": "Messages",
    "start": 30.453,
    "end": 30.964
  },
  {
    "word": "go",
    "start": 31.033,
    "end": 31.161
  },
  {
    "word": "to",
    "start": 31.207,
    "end": 31.254
  },
  {
    "word": "the",
    "start": 31.312,
    "end": 31.382
  },
  {
    "word": "email",
    "start": 31.451,
    "end": 31.811
  },
  {
    "word": "address",
    "start": 31.858,
    "end": 32.252
  },
  {
    "word": "on",
    "start": 32.322,
    "end": 32.496
  },
  {
    "word": "file",
    "start": 32.589,
    "end": 33.042
  },
  {
    "word": "in",
    "start": 33.111,
    "end": 33.239
  },
  {
    "word": "WISH",
    "start": 33.355,
    "end": 33.75
  },
  {
    "word": "—",
    "start": 34.029,
    "end": 34.33
  },
  {
    "word": "if",
    "start": 34.609,
    "end": 34.748
  },
  {
    "word": "an",
    "start": 34.795,
    "end": 34.853
  },
  {
    "word": "employee's",
    "start": 34.899,
    "end": 35.433
  },
  {
    "word": "email",
    "start": 35.515,
    "end": 35.84
  },
  {
    "word": "is",
    "start": 35.898,
    "end": 35.991
  },
  {
    "word": "outdated,",
    "start": 36.06,
    "end": 36.78
  },
  {
    "word": "they",
    "start": 36.85,
    "end": 37.012
  },
  {
    "word": "won't",
    "start": 37.07,
    "end": 37.279
  },
  {
    "word": "receive",
    "start": 37.325,
    "end": 37.685
  },
  {
    "word": "it",
    "start": 37.732,
    "end": 38.057
  },
  {
    "word": "•",
    "start": 38.057,
    "end": 38.382
  },
  {
    "word": "These",
    "start": 38.498,
    "end": 38.812
  },
  {
    "word": "are",
    "start": 38.846,
    "end": 38.974
  },
  {
    "word": "one-way",
    "start": 39.032,
    "end": 39.346
  },
  {
    "word": "communications",
    "start": 39.404,
    "end": 40.332
  },
  {
    "word": "—",
    "start": 40.507,
    "end": 43.456
  },
  {
    "word": "employees",
    "start": 44.756,
    "end": 45.673
  },
  {
    "word": "cannot",
    "start": 45.917,
    "end": 46.73
  },
  {
    "word": "reply",
    "start": 46.88,
    "end": 47.542
  },
  {
    "word": "through",
    "start": 47.751,
    "end": 48.297
  },
  {
    "word": "WISH",
    "start": 48.622,
    "end": 49.446
  },
  {
    "word": "•",
    "start": 49.446,
    "end": 51.211
  },
  {
    "word": "If",
    "start": 52.511,
    "end": 52.697
  },
  {
    "word": "an",
    "start": 52.755,
    "end": 52.813
  },
  {
    "word": "employee",
    "start": 52.86,
    "end": 53.533
  },
  {
    "word": "hasn't",
    "start": 53.614,
    "end": 53.986
  },
  {
    "word": "received",
    "start": 54.032,
    "end": 54.462
  },
  {
    "word": "a",
    "start": 54.508,
    "end": 54.531
  },
  {
    "word": "message",
    "start": 54.624,
    "end": 55.019
  },
  {
    "word": "you",
    "start": 55.066,
    "end": 55.147
  },
  {
    "word": "sent,",
    "start": 55.263,
    "end": 55.727
  },
  {
    "word": "verify",
    "start": 55.971,
    "end": 56.54
  },
  {
    "word": "their",
    "start": 56.61,
    "end": 56.772
  },
  {
    "word": "email",
    "start": 56.853,
    "end": 57.225
  },
  {
    "word": "address",
    "start": 57.271,
    "end": 57.666
  },
  {
    "word": "in",
    "start": 57.713,
    "end": 57.794
  },
  {
    "word": "their",
    "start": 57.84,
    "end": 57.991
  },
  {
    "word": "employee",
    "start": 58.038,
    "end": 58.549
  },
  {
    "word": "record",
    "start": 58.641,
    "end": 59.001
  },
  {
    "word": "before",
    "start": 59.059,
    "end": 59.582
  },
  {
    "word": "resending",
    "start": 59.675,
    "end": 60.65
  }
]